README.md
setup.py
iAROnline/__init__.py
iAROnline/methods.py
iAROnline/utils.py
iAROnline.egg-info/PKG-INFO
iAROnline.egg-info/SOURCES.txt
iAROnline.egg-info/dependency_links.txt
iAROnline.egg-info/not-zip-safe
iAROnline.egg-info/requires.txt
iAROnline.egg-info/top_level.txt